twitter_boto_dummy/data_analysis.py
twitter_boto_dummy/data_collection.py
twitter_boto_dummy/strategy_interface.py
twitter_boto_dummy/trends_data_collection.py
twitter_boto_dummy/twitter_account.py
twitter_boto_dummy/twitter_action.py
twitter_boto_dummy/twitter_api_preparation.py
twitter_boto_dummy/twitter_bot.py
twitter_boto_dummy/twitter_data_collection.py
twitter_boto_dummy/twitter_object_parsing.py
twitter_boto_dummy-0.0.1.dist-info/LICENSE
twitter_boto_dummy-0.0.1.dist-info/METADATA
twitter_boto_dummy-0.0.1.dist-info/WHEEL
twitter_boto_dummy-0.0.1.dist-info/top_level.txt
twitter_boto_dummy-0.0.1.dist-info/RECORD
